nasstat/__init__.py
nasstat/nasstat.py
nasstat-0.1.3.dist-info/licenses/LICENSE
nasstat-0.1.3.dist-info/METADATA
nasstat-0.1.3.dist-info/WHEEL
nasstat-0.1.3.dist-info/top_level.txt
nasstat-0.1.3.dist-info/RECORD
