Metadata-Version: 2.4
Name: nasstat
Version: 0.1.3
Summary: A python wrapper of the United States Federal Aviation Authority's National Airspace System API
Home-page: https://github.com/cruzdariel/nasstat
Author: Dariel Cruz Rodriguez
Author-email: hello@dariel.us
Classifier: Programming Language :: Python :: 3
Classifier: License :: OSI Approved :: MIT License
Classifier: Operating System :: OS Independent
Requires-Python: >=3.11
License-File: LICENSE
Requires-Dist: requests>=2.20.0
Requires-Dist: pytz>=2023.3
Dynamic: author
Dynamic: author-email
Dynamic: classifier
Dynamic: description
Dynamic: description-content-type
Dynamic: home-page
Dynamic: license-file
Dynamic: requires-dist
Dynamic: requires-python
Dynamic: summary
